fcpxml/__init__.py
fcpxml/fcp.py
fcpxml/utils.py
fcpxml-0.0.2.dist-info/LICENSE
fcpxml-0.0.2.dist-info/METADATA
fcpxml-0.0.2.dist-info/WHEEL
fcpxml-0.0.2.dist-info/top_level.txt
fcpxml-0.0.2.dist-info/RECORD
