Metadata-Version: 2.1
Name: fcpxml
Version: 0.0.2
Summary: fcpxml 解析
Home-page: https://github.com/ldsxp/fcpxml
Author: lds
Author-email: 85176878@qq.com
License: GNU GPL 3
Download-URL: https://pypi.org/project/fcpxml
Keywords: fcpxml,Final Cut Pro
Platform: any
Classifier: Development Status :: 1 - Planning
Classifier: Intended Audience :: Developers
Classifier: License :: OSI Approved :: GNU General Public License (GPL)
Classifier: Operating System :: OS Independent
Classifier: Programming Language :: Python
Classifier: Programming Language :: Python :: 3.6
Requires-Python: >=3.6
Provides-Extra: dev
Requires-Dist: wheel ; extra == 'dev'
Requires-Dist: twine ; extra == 'dev'
